drand_verify-0.2.1.dist-info/METADATA
drand_verify-0.2.1.dist-info/WHEEL
drand_verify-0.2.1.dist-info/license_files/LICENSE
drand_verify/__init__.py
drand_verify/drand_verify.cpython-39-x86_64-linux-gnu.so
drand_verify-0.2.1.dist-info/RECORD
