Metadata-Version: 2.1
Name: drand-verify
Version: 0.2.1
Classifier: Programming Language :: Rust
Classifier: Programming Language :: Python :: 3
Classifier: Programming Language :: Python :: Implementation :: CPython
Classifier: Programming Language :: Python :: Implementation :: PyPy
Classifier: License :: OSI Approved :: Apache Software License
License-File: LICENSE
Summary: Verify drand beacons and derive their randomness.
Keywords: drand,cryptography
Requires-Python: >=3.7
Project-URL: Homepage, https://github.com/very-lame-username/python-drand-verify
